KLKAMUSIC_CLI/__init__.py
KLKAMUSIC_CLI/install_script.py
KLKAMUSIC_CLI/klkamusic_cli.py
klkamusic_cli-0.1.5.dist-info/LICENSE
klkamusic_cli-0.1.5.dist-info/METADATA
klkamusic_cli-0.1.5.dist-info/WHEEL
klkamusic_cli-0.1.5.dist-info/entry_points.txt
klkamusic_cli-0.1.5.dist-info/top_level.txt
klkamusic_cli-0.1.5.dist-info/RECORD
