Metadata-Version: 2.2
Name: klkamusic_cli
Version: 0.1.5
Summary: A simple command-line music player for developers, that is built using yt-dlp and rich.
Home-page: https://github.com/kamalkoranga/music_cli.git
Author: Klka
Author-email: klka@duck.com
Classifier: Programming Language :: Python :: 3
Classifier: License :: OSI Approved :: MIT License
Classifier: Operating System :: OS Independent
License-File: LICENSE
Requires-Dist: yt-dlp
Requires-Dist: rich
Dynamic: author
Dynamic: author-email
Dynamic: classifier
Dynamic: home-page
Dynamic: requires-dist
Dynamic: summary
